ardeco_py_package/__init__.py
ardeco_py_package/__version__.py
ardeco_py_package/core.py
ardeco_py_package/exceptions.py
ardeco_py_package/functions.py
ardeco_py_package/models.py
ardeco_py_package-1.0.0.dist-info/licenses/LICENSE
ardeco_py_package-1.0.0.dist-info/METADATA
ardeco_py_package-1.0.0.dist-info/WHEEL
ardeco_py_package-1.0.0.dist-info/top_level.txt
ardeco_py_package-1.0.0.dist-info/RECORD
