Metadata-Version: 2.4
Name: ardeco-py-package
Version: 1.0.0
Summary: A Python SDK for the ARDECO Database API.
Author-email: European Commission <jrc-kctp@ec.europa.eu>
Maintainer-email: Ioris Bussolari <ioris.bussolari@ext.ec.europa.eu>, Lara Baggio <lara.baggio@ext.ec.europa.eu>
License: EUPL-1.2
Project-URL: Homepage, https://territorial.ec.europa.eu/ardeco
Project-URL: License, https://joinup.ec.europa.eu/collection/eupl/eupl-text-eupl-12
Requires-Python: >=3.9
License-File: LICENSE
Requires-Dist: pandas>=2.0
Requires-Dist: requests>=2.31
Dynamic: license-file
